{
    "name": "1.5-3.5-3-bp-noncausal",
    "constraints": [
        {
            "constraintType": "STRING",
            "criterion": "name",
            "operator": {
                "type": "EQ",
                "negated": false
            },
            "value": [
                "1.5 3.5 3 BP non-causal"
            ]
        }
    ],
    "parameters": {
        "name": "1.5 3.5 3 BP non-causal",
        "comments": "Butterworth IIR band-pass, 1.5-3.5 Hz, order 3, non-causal",
		"filterDescription": {
			"$ref=global.filter-description":[{ 
				"criterion": "name",
				"value": "1.5 3.5 3 BP non-causal Description"
			}]
		}
    }
}
